{
  "required": true,
  "minVersion": "0.8",
  "package": "mc.rpgstats.mixin",
  "plugin": "mc.rpgstats.mixin.compat.MixinCompatPlugin",
  "compatibilityLevel": "JAVA_16",
  "injectors": {
    "defaultRequire": 1
  },
  "mixins": [
    "ApplyDamageMixin",
    "BonemealGrowMixin",
    "BonemealMixin",
    "BowAccuracyMixin",
    "BowArrowMixin",
    "BowCanUseMixin",
    "DataFixerMixin",
    "FishingBobberMixin",
    "ImpalingMixin",
    "ItemEatMixin",
    "ItemStackHolderMixin",
    "KillMixin",
    "PotionDrinkMixin",
    "PotionSplashMixin",
    "ShearSheepMixin",
    "ShieldMixin",
    "StatusEffectsImmuneMixin",
    "SweetBerryHarvestMixin",
    "TakeDamageMixin",
    "TotemUseMixin",
    "UnbreakingEnchantmentMixin",
    "accessor.CriteriaAccessor",
    "compat.harvest.GrantFarmingOnSimpleHarvest"
  ]
}
